chaining/__init__.py
chaining/chain_list.py
chaining-0.0.2.dist-info/LICENSE
chaining-0.0.2.dist-info/METADATA
chaining-0.0.2.dist-info/WHEEL
chaining-0.0.2.dist-info/top_level.txt
chaining-0.0.2.dist-info/RECORD
