Metadata-Version: 2.1
Name: chaining
Version: 0.0.2
Summary: Package that implements functional chaining in Python, which behaves like JavaScript
Home-page: https://github.com/junhoyeo/chaining
Author: Junho Yeo
Author-email: hanaro0704@gmail.com
License: MIT
Download-URL: https://github.com/junhoyeo/chaining/archive/v_0.0.2.tar.gz
Keywords: functional,chaining
Platform: UNKNOWN
Classifier: Development Status :: 3 - Alpha
Classifier: Intended Audience :: Developers
Classifier: Topic :: Utilities
Classifier: License :: OSI Approved :: MIT License
Classifier: Programming Language :: Python :: 3.6
Classifier: Programming Language :: Python :: 3.7
Classifier: Programming Language :: Python :: 3.8
Requires-Python: >=3.6
